coegil/ApiService.py
coegil/Cli.py
coegil/__init__.py
CoegilCli-1.0.10.dist-info/METADATA
CoegilCli-1.0.10.dist-info/WHEEL
CoegilCli-1.0.10.dist-info/entry_points.txt
CoegilCli-1.0.10.dist-info/top_level.txt
CoegilCli-1.0.10.dist-info/RECORD
