Metadata-Version: 2.1
Name: CoegilCli
Version: 1.0.10
Summary: Coegil Command Line Interface
Home-page: https://coegil.com
Author: Mike Levine
Author-email: mike@coegil.com
Requires-Python: >=3.9
Requires-Dist: click
Requires-Dist: wheel
Requires-Dist: boto3
Requires-Dist: requests
Requires-Dist: coegil-sdk
